cognite/dm_clients/README.md
cognite/dm_clients/__init__.py
cognite/dm_clients/cdf/__init__.py
cognite/dm_clients/cdf/client_dm_v3.py
cognite/dm_clients/cdf/data_classes_dm_v3.py
cognite/dm_clients/cdf/get_client.py
cognite/dm_clients/config.py
cognite/dm_clients/custom_types/__init__.py
cognite/dm_clients/custom_types/_scalars.py
cognite/dm_clients/custom_types/jsonobject.py
cognite/dm_clients/custom_types/timestamp.py
cognite/dm_clients/domain_modeling/__init__.py
cognite/dm_clients/domain_modeling/domain_client.py
cognite/dm_clients/domain_modeling/domain_model.py
cognite/dm_clients/domain_modeling/domain_model_api.py
cognite/dm_clients/domain_modeling/relationship_api.py
cognite/dm_clients/domain_modeling/schema.py
cognite/dm_clients/domain_modeling/testing.py
cognite/dm_clients/misc.py
cognite/dm_clients/py.typed
cognite/gqlpygen/__init__.py
cognite/gqlpygen/data_classes.py
cognite/gqlpygen/generator.py
cognite/gqlpygen/main.py
cognite/gqlpygen/misc.py
cognite/gqlpygen/parser.py
cognite/gqlpygen/templates/client.txt
cognite/gqlpygen/templates/schema.txt
cognite/gqlpygen/version.py
cognite_gql_pygen-0.8.1.dist-info/LICENSE
cognite_gql_pygen-0.8.1.dist-info/METADATA
cognite_gql_pygen-0.8.1.dist-info/WHEEL
cognite_gql_pygen-0.8.1.dist-info/entry_points.txt
cognite_gql_pygen-0.8.1.dist-info/RECORD
