Metadata-Version: 2.1
Name: cognite-gql-pygen
Version: 0.8.1
Summary: Cognite GraphQL Python Generation SDK
License: Apache-2.0
Author: Cognite
Author-email: support@cognite.com
Requires-Python: >=3.9,<4.0
Classifier: License :: OSI Approved :: Apache Software License
Classifier: Programming Language :: Python :: 3
Classifier: Programming Language :: Python :: 3.9
Classifier: Programming Language :: Python :: 3.10
Classifier: Programming Language :: Python :: 3.11
Provides-Extra: all
Provides-Extra: cli
Requires-Dist: Jinja2 (>=3.1)
Requires-Dist: cachelib (>=0.10.2)
Requires-Dist: cognite-sdk (>5.9.0)
Requires-Dist: dynaconf (>=3.1.12)
Requires-Dist: graphql-core (>=3.2)
Requires-Dist: msal (>=1.16.0)
Requires-Dist: packaging (>=21.3) ; extra == "cli" or extra == "all"
Requires-Dist: pydantic (>=1.10)
Requires-Dist: retry (>=0.9.2)
Requires-Dist: strawberry-graphql (>=0.156.4,<0.157.0)
Requires-Dist: toml (>=0.10)
Requires-Dist: typer[rich] (>=0.9) ; extra == "cli" or extra == "all"
Requires-Dist: typing-extensions (>=4.4.0)
